{
  "source": "0338_Manual_Stickynote_Export_Webhook.json",
  "index": 1,
  "content": "{\n  \"id\": \"1U5Jf4NMQEw9LtxY\",\n  \"meta\": {\n    \"instanceId\": \"885b4fb4a6a9c2cb5621429a7b972df0d05bb724c20ac7dac7171b62f1c7ef40\"\n  },\n  \"name\": \"Capture Website Screenshots with Bright Data Web Unlocker and Save to Disk\",\n  \"tags\": [\n    {\n      \"id\": \"Kujft2FOjmOVQAmJ\",\n      \"name\": \"Engineering\",\n      \"createdAt\": \"2025-04-09T01:31:00.558Z\",\n      \"updatedAt\": \"2025-04-09T01:31:00.558Z\"\n    }\n  ],\n  \"nodes\": [\n    {\n      \"id\": \"d61cb066-1d5f-47d5-a4dd-4534f3d3c6d8\",\n      \"name\": \"When clicking ‘Test workflow’\",\n      \"type\": \"n8n-nodes-base.manualTrigger\",\n      \"position\": [\n        -520,\n        -160\n      ],\n      \"parameters\": {},\n      \"typeVersion\": 1\n    },\n    {\n      \"id\": \"eb99305b-0375-4cdd-8682-637d281598a0\",\n      \"name\": \"Sticky Note\",\n      \"type\": \"n8n-nodes-base.stickyNote\",\n      \"position\": [\n        -540,\n        -500\n      ],\n      \"parameters\": {\n        \"width\": 360,\n        \"height\": 260,\n        \"content\": \"## Note\\n\\nThe \\\"**Set URL, Filename and Bright Data Zone**\\\" node must be updated with the appropriate url, file name and **Bright Data Proxies & Infrastructure** zone.\\n\\nThe \\\"**Write a file to disk**\\\" node has the location to download the website screenshot. Please make sure to set the path\"\n      },\n      \"typeVersion\": 1\n    },\n    {\n      \"id\": \"205f64e9-5b31-4c76-912a-307eccde159e\",\n      \"name\": \"Sticky Note1\",\n      \"type\": \"n8n-nodes-base.stickyNote\",\n      \"position\": [\n        -160,\n        -240\n      ],\n      \"parameters\": {\n        \"color\": 4,\n        \"width\": 260,\n        \"height\": 280,\n        \"content\": \"## Website Screenshot\"\n      },\n      \"typeVersion\": 1\n    },\n    {\n      \"id\": \"e7705941-2ae8-4c38-93cb-2cb865314872\",\n      \"name\": \"Write a file to disk\",\n      \"type\": \"n8n-nodes-base.readWriteFile\",\n      \"position\": [\n        140,\n        -160\n      ],\n      \"parameters\": {\n        \"options\": {},\n        \"fileName\": \"={{ \\\"c:\\\\\\\\\\\"+ $json.filename }}\",\n        \"operation\": \"write\",\n        \"dataPropertyName\": \"={{ $json.filename }}\"\n      },\n      \"typeVersion\": 1\n    },\n    {\n      \"id\": \"167ff255-da5b-43c1-a22f-e00c4cc166d8\",\n      \"name\": \"Capture a screenshot\",\n      \"type\": \"n8n-nodes-base.httpRequest\",\n      \"position\": [\n        -80,\n        -160\n      ],\n      \"parameters\": {\n        \"url\": \"https://api.brightdata.com/request\",\n        \"method\": \"POST\",\n        \"options\": {\n          \"response\": {\n            \"response\": {\n              \"responseFormat\": \"file\",\n              \"outputPropertyName\": \"={{ $json.filename }}\"\n            }\n          },\n          \"allowUnauthorizedCerts\": true\n        },\n        \"sendBody\": true,\n        \"sendHeaders\": true,\n        \"authentication\": \"genericCredentialType\",\n        \"bodyParameters\": {\n          \"parameters\": [\n            {\n              \"name\": \"zone\",\n              \"value\": \"={{ $json.zone }}\"\n            },\n            {\n              \"name\": \"url\",\n              \"value\": \"={{ $json.url }}\"\n            },\n            {\n              \"name\": \"format\",\n              \"value\": \"raw\"\n            },\n            {\n              \"name\": \"data_format\",\n              \"value\": \"screenshot\"\n            }\n          ]\n        },\n        \"genericAuthType\": \"httpHeaderAuth\",\n        \"headerParameters\": {\n          \"parameters\": [\n            {}\n          ]\n        }\n      },\n      \"credentials\": {\n        \"httpHeaderAuth\": {\n          \"id\": \"kdbqXuxIR8qIxF7y\",\n          \"name\": \"Header Auth account\"\n        }\n      },\n      \"typeVersion\": 4.2\n    },\n    {\n      \"id\": \"1c5c3d72-f20d-4d06-a6f2-461d043c4a01\",\n      \"name\": \"Set URL, Filename and Bright Data Zone\",\n      \"type\": \"n8n-nodes-base.set\",\n      \"position\": [\n        -300,\n        -160\n      ],\n      \"parameters\": {\n        \"options\": {},\n        \"assignments\": {\n          \"assignments\": [\n            {\n              \"id\": \"c9de0c3e-609a-4e87-b6ab-b4312be026a9\",\n              \"name\": \"url\",\n              \"type\": \"string\",\n              \"value\": \"https://dev.to/\"\n            },\n            {\n              \"id\": \"408ed65a-0d66-4f98-b2eb-0d5e066e3250\",\n              \"name\": \"filename\",\n              \"type\": \"string\",\n              \"value\": \"devto.png\"\n            },\n            {\n              \"id\": \"ee10fcb0-a610-4987-8a4e-dfab077aee0e\",\n              \"name\": \"zone\",\n              \"type\": \"string\",\n              \"value\": \"web_unlocker1\"\n            }\n          ]\n        }\n      },\n      \"typeVersion\": 3.4\n    }\n  ],\n  \"active\": false,\n  \"pinData\": {},\n  \"settings\": {\n    \"executionOrder\": \"v1\"\n  },\n  \"versionId\": \"d3ae63f2-efcf-478b-aadf-8a3fac2af02a\",\n  \"connections\": {\n    \"Capture a screenshot\": {\n      \"main\": [\n        [\n          {\n            \"node\": \"Write a file to disk\",\n            \"type\": \"main\",\n            \"index\": 0\n          }\n        ]\n      ]\n    },\n    \"When clicking ‘Test workflow’\": {\n      \"main\": [\n        [\n          {\n            \"node\": \"Set URL, Filename and Bright Data Zone\",\n            \"type\": \"main\",\n            \"index\": 0\n          }\n        ]\n      ]\n    },\n    \"Set URL, Filename and Bright Data Zone\": {\n      \"main\": [\n        [\n          {\n            \"node\": \"Capture a screenshot\",\n            \"type\": \"main\",\n            \"index\": 0\n          }\n        ]\n      ]\n    }\n  }\n}",
  "metadata": {
    "node_types": [
      "n8n-nodes-base.manualTrigger",
      "n8n-nodes-base.stickyNote",
      "n8n-nodes-base.stickyNote",
      "n8n-nodes-base.readWriteFile",
      "n8n-nodes-base.httpRequest",
      "n8n-nodes-base.set"
    ],
    "trigger": null
  }
}