{
  "source": "0616_Elasticsearch_Cron_Create_Webhook.json",
  "index": 1,
  "content": "{\n  \"meta\": {\n    \"instanceId\": \"43da491ee7afc3232a99276a123dc774d0498da8891013b60e82828d6f1f40c7\"\n  },\n  \"nodes\": [\n    {\n      \"id\": \"77af14bb-db74-4069-adcc-d66e3bb3f893\",\n      \"name\": \"Cron Trigger\",\n      \"type\": \"n8n-nodes-base.cron\",\n      \"position\": [\n        400,\n        300\n      ],\n      \"parameters\": {\n        \"triggerTimes\": {\n          \"item\": [\n            {\n              \"hour\": 12,\n              \"minute\": 15\n            }\n          ]\n        }\n      },\n      \"typeVersion\": 1\n    },\n    {\n      \"id\": \"286b8b82-78c5-458a-b708-79f0b7d1437c\",\n      \"name\": \"Elasticsearch Query\",\n      \"type\": \"n8n-nodes-base.elasticsearch\",\n      \"position\": [\n        600,\n        300\n      ],\n      \"parameters\": {\n        \"options\": {}\n      },\n      \"typeVersion\": 1\n    },\n    {\n      \"id\": \"425719a5-41d2-4f3a-80ba-241620d9f793\",\n      \"name\": \"Check for Alerts\",\n      \"type\": \"n8n-nodes-base.if\",\n      \"position\": [\n        800,\n        300\n      ],\n      \"parameters\": {\n        \"conditions\": {\n          \"number\": [\n            {\n              \"value1\": \"={{$json[\\\"hits\\\"][\\\"total\\\"][\\\"value\\\"]}}\",\n              \"operation\": \"greater\"\n            }\n          ]\n        }\n      },\n      \"typeVersion\": 1\n    },\n    {\n      \"id\": \"a2c6bd3d-c65d-4653-8183-9525a4c3af79\",\n      \"name\": \"Create Work Item\",\n      \"type\": \"n8n-nodes-base.httpRequest\",\n      \"position\": [\n        1040,\n        280\n      ],\n      \"parameters\": {\n        \"url\": \"https://dev.azure.com/<organization>/<project>/_apis/wit/workitems/$Task?api-version=7.1-preview.3\",\n        \"options\": {},\n        \"authentication\": \"basicAuth\",\n        \"headerParametersUi\": {\n          \"parameter\": [\n            {\n              \"name\": \"Content-Type\",\n              \"value\": \"application/json-patch+json\"\n            }\n          ]\n        }\n      },\n      \"typeVersion\": 1\n    },\n    {\n      \"id\": \"71ee087f-4f75-4544-b26a-95c7ce12d020\",\n      \"name\": \"No Operation, do nothing\",\n      \"type\": \"n8n-nodes-base.noOp\",\n      \"position\": [\n        1060,\n        460\n      ],\n      \"parameters\": {},\n      \"typeVersion\": 1\n    }\n  ],\n  \"pinData\": {},\n  \"connections\": {\n    \"Cron Trigger\": {\n      \"main\": [\n        [\n          {\n            \"node\": \"Elasticsearch Query\",\n            \"type\": \"main\",\n            \"index\": 0\n          }\n        ]\n      ]\n    },\n    \"Check for Alerts\": {\n      \"main\": [\n        [\n          {\n            \"node\": \"Create Work Item\",\n            \"type\": \"main\",\n            \"index\": 0\n          }\n        ],\n        [\n          {\n            \"node\": \"No Operation, do nothing\",\n            \"type\": \"main\",\n            \"index\": 0\n          }\n        ]\n      ]\n    },\n    \"Elasticsearch Query\": {\n      \"main\": [\n        [\n          {\n            \"node\": \"Check for Alerts\",\n            \"type\": \"main\",\n            \"index\": 0\n          }\n        ]\n      ]\n    }\n  }\n}",
  "metadata": {
    "node_types": [
      "n8n-nodes-base.cron",
      "n8n-nodes-base.elasticsearch",
      "n8n-nodes-base.if",
      "n8n-nodes-base.httpRequest",
      "n8n-nodes-base.noOp"
    ],
    "trigger": "cron trigger"
  }
}