{
  "source": "0842_Twilio_Cron_Send_Scheduled.json",
  "index": 1,
  "content": "{\n  \"id\": \"34\",\n  \"name\": \"Monitoring and alerting\",\n  \"nodes\": [\n    {\n      \"name\": \"Cron\",\n      \"type\": \"n8n-nodes-base.cron\",\n      \"position\": [\n        250,\n        200\n      ],\n      \"parameters\": {},\n      \"typeVersion\": 1\n    },\n    {\n      \"name\": \"Postgres\",\n      \"type\": \"n8n-nodes-base.postgres\",\n      \"position\": [\n        450,\n        200\n      ],\n      \"parameters\": {\n        \"query\": \"SELECT * FROM n8n WHERE value > 70 AND notification = false;\",\n        \"operation\": \"executeQuery\"\n      },\n      \"credentials\": {\n        \"postgres\": \"Postgres\"\n      },\n      \"typeVersion\": 1\n    },\n    {\n      \"name\": \"Twilio\",\n      \"type\": \"n8n-nodes-base.twilio\",\n      \"position\": [\n        650,\n        200\n      ],\n      \"parameters\": {\n        \"to\": \"\",\n        \"from\": \"\",\n        \"message\": \"=🚨 The Sensor ({{$node[\\\"Postgres\\\"].json[\\\"sensor_id\\\"]}}) showed a reading of {{$node[\\\"Postgres\\\"].json[\\\"value\\\"]}}.\"\n      },\n      \"credentials\": {\n        \"twilioApi\": \"Twilio\"\n      },\n      \"typeVersion\": 1\n    },\n    {\n      \"name\": \"Set\",\n      \"type\": \"n8n-nodes-base.set\",\n      \"position\": [\n        850,\n        200\n      ],\n      \"parameters\": {\n        \"values\": {\n          \"number\": [\n            {\n              \"name\": \"id\",\n              \"value\": \"={{$node[\\\"Postgres\\\"].json[\\\"id\\\"]}}\"\n            }\n          ],\n          \"boolean\": [\n            {\n              \"name\": \"notification\",\n              \"value\": true\n            }\n          ]\n        },\n        \"options\": {},\n        \"keepOnlySet\": true\n      },\n      \"typeVersion\": 1\n    },\n    {\n      \"name\": \"Postgres1\",\n      \"type\": \"n8n-nodes-base.postgres\",\n      \"position\": [\n        1050,\n        200\n      ],\n      \"parameters\": {\n        \"table\": \"n8n\",\n        \"columns\": \"notification\",\n        \"operation\": \"update\"\n      },\n      \"credentials\": {\n        \"postgres\": \"Postgres\"\n      },\n      \"typeVersion\": 1\n    }\n  ],\n  \"active\": false,\n  \"settings\": {},\n  \"connections\": {\n    \"Set\": {\n      \"main\": [\n        [\n          {\n            \"node\": \"Postgres1\",\n            \"type\": \"main\",\n            \"index\": 0\n          }\n        ]\n      ]\n    },\n    \"Cron\": {\n      \"main\": [\n        [\n          {\n            \"node\": \"Postgres\",\n            \"type\": \"main\",\n            \"index\": 0\n          }\n        ]\n      ]\n    },\n    \"Twilio\": {\n      \"main\": [\n        [\n          {\n            \"node\": \"Set\",\n            \"type\": \"main\",\n            \"index\": 0\n          }\n        ]\n      ]\n    },\n    \"Postgres\": {\n      \"main\": [\n        [\n          {\n            \"node\": \"Twilio\",\n            \"type\": \"main\",\n            \"index\": 0\n          }\n        ]\n      ]\n    }\n  }\n}",
  "metadata": {
    "node_types": [
      "n8n-nodes-base.cron",
      "n8n-nodes-base.postgres",
      "n8n-nodes-base.twilio",
      "n8n-nodes-base.set",
      "n8n-nodes-base.postgres"
    ],
    "trigger": null
  }
}