{
  "source": "docs/integrations/creating-nodes/build/declarative-style-node.md",
  "index": 12,
  "content": "### Step 6: Update the npm package details\n\nYour npm package details are in the `package.json` at the root of the project. It's essential to include the `n8n` object with links to the credentials and base node file. Update this file to include the following information:\n\n```json\n{\n\t// All node names must start with \"n8n-nodes-\"\n\t\"name\": \"n8n-nodes-nasapics\",\n\t\"version\": \"0.1.0\",\n\t\"description\": \"n8n node to call NASA's APOD and Mars Rover Photo services.\",\n\t\"keywords\": [\n\t\t// This keyword is required for community nodes\n\t\t\"n8n-community-node-package\"\n\t],\n\t\"license\": \"MIT\",\n\t\"homepage\": \"https://n8n.io\",\n\t\"author\": {\n\t\t\"name\": \"Test\",\n\t\t\"email\": \"test@example.com\"\n\t},\n\t\"repository\": {\n\t\t\"type\": \"git\",\n\t\t// Change the git remote to your own repository\n\t\t// Add the new URL here\n\t\t\"url\": \"git+<your-repo-url>\"\n\t},\n\t\"main\": \"index.js\",\n\t\"scripts\": {\n\t\t// don't change\n\t},\n\t\"files\": [\n\t\t\"dist\"\n\t],\n\t// Link the credentials and node\n\t\"n8n\": {\n\t\t\"n8nNodesApiVersion\": 1,\n\t\t\"credentials\": [\n\t\t\t\"dist/credentials/NasaPicsApi.credentials.js\"\n\t\t],\n\t\t\"nodes\": [\n\t\t\t\"dist/nodes/NasaPics/NasaPics.node.js\"\n\t\t]\n\t},\n\t\"devDependencies\": {\n\t\t// don't change\n\t},\n\t\"peerDependencies\": {\n\t\t// don't change\n\t}\n}\n```\n\nYou need to update the `package.json` to include your own information, such as your name and repository URL. For more information on npm `package.json` files, refer to [npm's package.json documentation](https://docs.npmjs.com/cli/v8/configuring-npm/package-json)."
}